topsis/__init__.py
topsis/topsis.py
topsis_bhavya_102303560-1.0.3.dist-info/METADATA
topsis_bhavya_102303560-1.0.3.dist-info/WHEEL
topsis_bhavya_102303560-1.0.3.dist-info/entry_points.txt
topsis_bhavya_102303560-1.0.3.dist-info/top_level.txt
topsis_bhavya_102303560-1.0.3.dist-info/RECORD
