Metadata-Version: 2.4
Name: Topsis-bhavya-102303560
Version: 1.0.3
Summary: TOPSIS implementation using Python
Author: Bhavya
Requires-Dist: pandas
Requires-Dist: numpy
Dynamic: author
Dynamic: description
Dynamic: description-content-type
Dynamic: requires-dist
Dynamic: summary
